xmltocd/__init__.py
xmltocd/_collections.py
xmltocd/_decorator.py
xmltocd/_exception.py
xmltocd/_ntype.py
xmltocd/_parse.py
xmltocd/_rely.py
xmltocd/_tools.py
xmltocd/manager.py
xmltocd/struct.py
xmltocd-0.2.3.2.dist-info/LICENSE
xmltocd-0.2.3.2.dist-info/METADATA
xmltocd-0.2.3.2.dist-info/WHEEL
xmltocd-0.2.3.2.dist-info/top_level.txt
xmltocd-0.2.3.2.dist-info/RECORD
