Metadata-Version: 2.1
Name: xmltocd
Version: 0.2.3.2
Summary: An effective, powerful, fast and simple XML Python parsing tool.
Home-page: https://github.com/JIYANG-PLUS/xml-to-chain-dict
Author: jiyang
Author-email: jiyangj@foxmail.com
License: UNKNOWN
Platform: UNKNOWN
Classifier: Programming Language :: Python :: 3
Classifier: License :: OSI Approved :: MIT License
Classifier: Operating System :: OS Independent
License-File: LICENSE
